{"tool_name":"annovar","contents":["biotools","bioschemas"],"page_metadata":{"biotools":{"id":"annovar","home":"http://annovar.openbioinformatics.org/en/latest/","license":null,"summary":"A tool for finding relevant genetic variants from high-throughput sequencing data based on functional annotation.","addition_date":"2017-01-13T13:13:33Z","last_update_date":"2024-11-24T15:58:06.017046Z","tool_type":["Command-line tool","Web service"],"version":null},"bioschemas":{"name":"ANNOVAR","home":"https://bio.tools/annovar","license":null,"version":null,"summary":"A tool for finding relevant genetic variants from high-throughput sequencing data based on functional annotation.","tool_type":"sc:SoftwareApplication"}}}