{"tool_name":"associationsubgraphs","contents":["bioschemas","biotools"],"page_metadata":{"biotools__id":"associationsubgraphs","biotools__home":"https://prod.tbilab.org/associationsubgraphs_info/","biotools__license":"MIT","biotools__summary":"Interactive network-based clustering and investigation of multimorbidity association matrices with associationSubgraphs.","biotools__addition_date":"2023-02-11T07:48:23.766272Z","biotools__last_update_date":"2023-02-11T07:48:23.768942Z","biotools__tool_type":["Library"],"bioschemas__name":"associationSubgraphs","bioschemas__home":"https://bio.tools/associationsubgraphs","bioschemas__license":"MIT","bioschemas__summary":"Interactive network-based clustering and investigation of multimorbidity association matrices with associationSubgraphs.","bioschemas__tool_type":"sc:SoftwareApplication"}}