{"tool_name":"atcc","contents":["bioschemas","biotools"],"page_metadata":{"biotools__id":"atcc","biotools__home":"http://www.lgcstandards-atcc.org/","biotools__summary":"Global biological materials resource and standards organization whose mission focuses on the acquisition, authentication, production, preservation, development, and distribution of standard reference microorganisms, cell lines, and other materials.","biotools__addition_date":"2015-09-11T18:49:07Z","biotools__last_update_date":"2018-12-10T12:58:49Z","biotools__tool_type":["Database portal"],"bioschemas__name":"American Type Culture Collection (ATCC)","bioschemas__home":"https://bio.tools/atcc","bioschemas__summary":"Global biological materials resource and standards organization whose mission focuses on the acquisition, authentication, production, preservation, development, and distribution of standard reference microorganisms, cell lines, and other materials.","bioschemas__tool_type":"sc:SoftwareApplication"}}