{"tool_name":"b3db","contents":["bioschemas","biotools"],"page_metadata":{"biotools__id":"b3db","biotools__home":"https://github.com/theochem/B3DB","biotools__license":"CC0-1.0","biotools__summary":"Blood-Brain Barrier Database (B3DB) is a curated diverse molecular database of blood-brain barrier permeability with chemical descriptors.","biotools__addition_date":"2022-03-28T10:26:21.061360Z","biotools__last_update_date":"2022-03-28T10:26:21.064005Z","biotools__tool_type":["Script"],"bioschemas__name":"B3DB","bioschemas__home":"https://bio.tools/b3db","bioschemas__license":"CC0-1.0","bioschemas__summary":"Blood-Brain Barrier Database (B3DB) is a curated diverse molecular database of blood-brain barrier permeability with chemical descriptors.","bioschemas__tool_type":"sc:SoftwareApplication"}}