{"tool_name":"binary-volumes","contents":["biotools","bioschemas"],"page_metadata":{"biotools__id":"binary-volumes","biotools__home":"https://www.mathworks.com/matlabcentral/fileexchange/35788-get-binary-volumes-from-a-volume-of-labels-integers","biotools__summary":"Creates a set of binary volumes from a volume of labels (integers value)","biotools__addition_date":"2021-05-05T11:10:00Z","biotools__last_update_date":"2021-05-23T10:53:55Z","biotools__tool_type":["Library"],"biotools__version":["1.0.0.0"]}}