{"tool_name":"biscap","contents":["bioschemas","biotools"],"page_metadata":{"biotools__id":"biscap","biotools__home":"https://github.com/diogonarciso/BISCAP","biotools__license":"Not licensed","biotools__summary":"BISCAP (Biofilm Imaging and Structure Classification Automatic Processor) a high-fidelity strategy for the automatic processing of 2D OCT biofilm.","biotools__addition_date":"2022-06-09T08:21:33.388631Z","biotools__last_update_date":"2022-06-09T08:21:33.392735Z","biotools__tool_type":["Desktop application"],"bioschemas__name":"BISCAP","bioschemas__home":"https://bio.tools/biscap","bioschemas__license":"Not licensed","bioschemas__summary":"BISCAP (Biofilm Imaging and Structure Classification Automatic Processor) a high-fidelity strategy for the automatic processing of 2D OCT biofilm.","bioschemas__tool_type":"sc:SoftwareApplication"}}