{"tool_name":"bnd","contents":["biotools","bioschemas"],"page_metadata":{"biotools__id":"bnd","biotools__home":"http://www.csbio.sjtu.edu.cn/bioinf/BND/","biotools__summary":"New balanced network deconvolution algorithm to identify optimized dependency matrix without limit on the eigenvalue range in the applied network systems. The algorithm was used to filter contact predictions of five widely-used co-evolution methods.","biotools__addition_date":"2017-08-03T18:37:04Z","biotools__last_update_date":"2024-11-25T15:15:40.637303Z","biotools__tool_type":["Web application"],"bioschemas__name":"BND","bioschemas__home":"https://bio.tools/bnd","bioschemas__summary":"New balanced network deconvolution algorithm to identify optimized dependency matrix without limit on the eigenvalue range in the applied network systems. The algorithm was used to filter contact predictions of five widely-used co-evolution methods.","bioschemas__tool_type":"sc:SoftwareApplication"}}