{"tool_name":"cancersubtypes","contents":["biotools","bioschemas"],"page_metadata":{"biotools":{"id":"cancersubtypes","home":"http://bioconductor.org/packages/release/bioc/html/CancerSubtypes.html","license":"GPL-2.0","summary":"This tool integrates the current common computational biology methods for cancer subtypes identification and provides a standarized framework for cancer subtypes analysis based on genomic datasets.","addition_date":"2017-01-17T14:55:13Z","last_update_date":"2024-11-25T15:55:11.855201Z","tool_type":["Command-line tool","Library"],"version":["1.0.0"]},"bioschemas":{"name":"CancerSubtypes","home":"https://bio.tools/cancersubtypes","license":"GPL-2.0","version":"1.0.0","summary":"This tool integrates the current common computational biology methods for cancer subtypes identification and provides a standarized framework for cancer subtypes analysis based on genomic datasets.","tool_type":"sc:SoftwareApplication"}}}