{"tool_name":"cellchat","contents":["bioschemas","biotools"],"page_metadata":{"biotools__id":"cellchat","biotools__home":"https://github.com/sqjin/CellChat","biotools__summary":"CellChat is a R toolkit for inference, visualization and analysis of cell-cell communication from single-cell data","biotools__addition_date":"2021-01-18T09:54:01Z","biotools__last_update_date":"2021-02-10T12:38:25Z","biotools__tool_type":["Library"],"bioschemas__name":"CellChat","bioschemas__home":"https://bio.tools/cellchat","bioschemas__summary":"CellChat is a R toolkit for inference, visualization and analysis of cell-cell communication from single-cell data","bioschemas__tool_type":"sc:SoftwareApplication"}}