{"tool_name":"chip-atlas","contents":["biotools","bioschemas"],"page_metadata":{"biotools__id":"chip-atlas","biotools__home":"https://chip-atlas.org","biotools__license":"MIT","biotools__summary":"ChIP-Atlas is a web service providing both GUI- and API-based data-mining tools to reveal the architecture of the transcription regulatory landscape.","biotools__addition_date":"2022-06-22T07:44:41.710755Z","biotools__last_update_date":"2024-11-24T20:07:33.436374Z","biotools__tool_type":["Database portal","Suite","Web application"],"bioschemas__name":"ChIP-Atlas","bioschemas__home":"https://bio.tools/chip-atlas","bioschemas__license":"MIT","bioschemas__summary":"ChIP-Atlas is a web service providing both GUI- and API-based data-mining tools to reveal the architecture of the transcription regulatory landscape.","bioschemas__tool_type":"sc:SoftwareApplication"}}