{"tool_name":"clarity","contents":["bioschemas","biotools"],"page_metadata":{"biotools__id":"clarity","biotools__home":"http://github.com/danjlawson/CLARITY","biotools__license":"GPL-3.0","biotools__summary":"Clarity: An R package for Comparing SimiLARITY Matrices and comparing heterogeneous data using dissimilarity.","biotools__addition_date":"2022-06-06T11:37:02.661941Z","biotools__last_update_date":"2022-06-06T11:37:02.664428Z","biotools__tool_type":["Library"],"bioschemas__name":"CLARITY","bioschemas__home":"https://bio.tools/clarity","bioschemas__license":"GPL-3.0","bioschemas__summary":"Clarity: An R package for Comparing SimiLARITY Matrices and comparing heterogeneous data using dissimilarity.","bioschemas__tool_type":"sc:SoftwareApplication"}}