{"tool_name":"clumpak","contents":["biotools","bioschemas"],"page_metadata":{"biotools__id":"clumpak","biotools__home":"http://clumpak.tau.ac.il/","biotools__license":"Not licensed","biotools__summary":"Clustering Markov Packager Across K- was developed in order to aid users analyse the results of STRUCTURE-like programs. The main pipeline offers a full pipeline for the summation and graphical representation of the results previously obtained by the user using a STRUCTURE-like program.","biotools__addition_date":"2017-08-20T15:20:59Z","biotools__last_update_date":"2024-11-25T14:01:43.311861Z","biotools__tool_type":["Web application"],"bioschemas__name":"CLUMPAK","bioschemas__home":"https://bio.tools/clumpak","bioschemas__license":"Not licensed","bioschemas__summary":"Clustering Markov Packager Across K- was developed in order to aid users analyse the results of STRUCTURE-like programs. The main pipeline offers a full pipeline for the summation and graphical representation of the results previously obtained by the user using a STRUCTURE-like program.","bioschemas__tool_type":"sc:SoftwareApplication"}}