{"tool_name":"cobrac","contents":["biotools","bioschemas"],"page_metadata":{"biotools__id":"cobrac","biotools__home":"https://cvxbiclustr.ericchi.com","biotools__license":"GPL-3.0","biotools__summary":"COBRAC is a fast implementation of convex biclustering with compression","biotools__addition_date":"2021-06-14T13:10:18Z","biotools__last_update_date":"2024-11-24T20:20:00.931282Z","biotools__tool_type":["Web application"],"bioschemas__name":"COBRAC","bioschemas__home":"https://bio.tools/cobrac","bioschemas__license":"GPL-3.0","bioschemas__summary":"COBRAC is a fast implementation of convex biclustering with compression","bioschemas__tool_type":"sc:SoftwareApplication"}}