{"tool_name":"cobrapy","contents":["biotools","bioschemas"],"page_metadata":{"biotools__id":"cobrapy","biotools__home":"https://github.com/opencobra/cobrapy","biotools__license":"GPL-3.0","biotools__summary":"COnstraints-Based Reconstruction and Analysis for Python.","biotools__addition_date":"2018-04-29T10:20:37Z","biotools__last_update_date":"2022-05-04T09:45:45.501716Z","biotools__tool_type":["Command-line tool"],"bioschemas__name":"COBRApy","bioschemas__home":"https://bio.tools/cobrapy","bioschemas__license":"GPL-3.0","bioschemas__summary":"COnstraints-Based Reconstruction and Analysis for Python.","bioschemas__tool_type":"sc:SoftwareApplication"}}