{"tool_name":"copub","contents":["biotools","bioschemas"],"page_metadata":{"biotools__id":"copub","biotools__home":"http://www.copub.org","biotools__summary":"Text mining tool for the detection of biomedical terms that co-occur in abstracts with the list of input genes (human, rat, and mouse genes). It also graphically displays differentially expressed genes and over-represented keywords in a network for better visualization of relationships. Version 5.0 uses a new thesauri. It allows for searching of keywords, provides highlighting and sorting mechanisms and statistics. It searches for indirect relations between genes, pathways, drugs and diseases.","biotools__addition_date":"2017-02-14T09:36:49Z","biotools__last_update_date":"2024-11-25T16:18:57.163241Z","biotools__tool_type":["Web application"],"bioschemas__name":"CoPub","bioschemas__home":"https://bio.tools/copub","bioschemas__summary":"Text mining tool for the detection of biomedical terms that co-occur in abstracts with the list of input genes (human, rat, and mouse genes). It also graphically displays differentially expressed genes and over-represented keywords in a network for better visualization of relationships. Version 5.0 uses a new thesauri. It allows for searching of keywords, provides highlighting and sorting mechanisms and statistics. It searches for indirect relations between genes, pathways, drugs and diseases.","bioschemas__tool_type":"sc:SoftwareApplication"}}