{"tool_name":"covasim","contents":["biotools","bioschemas"],"page_metadata":{"biotools__id":"covasim","biotools__home":"https://app.covasim.org/","biotools__license":"CC-BY-SA-4.0","biotools__summary":"Covasim is a stochastic agent-based simulator designed to be used for COVID-19 (novel coronavirus, SARS-CoV-2) epidemic analyses. These include projections of indicators such as numbers of infections and peak hospital demand. Covasim can also be used to explore the potential impact of different interventions, including social distancing, school closures, testing, contact tracing, quarantine, and vaccination.","biotools__addition_date":"2021-01-18T09:08:07Z","biotools__last_update_date":"2021-02-17T19:06:41Z","biotools__tool_type":["Web application"],"bioschemas__name":"Covasim","bioschemas__home":"https://bio.tools/covasim","bioschemas__license":"CC-BY-SA-4.0","bioschemas__summary":"Covasim is a stochastic agent-based simulator designed to be used for COVID-19 (novel coronavirus, SARS-CoV-2) epidemic analyses. These include projections of indicators such as numbers of infections and peak hospital demand. Covasim can also be used to explore the potential impact of different interventions, including social distancing, school closures, testing, contact tracing, quarantine, and vaccination.","bioschemas__tool_type":"sc:SoftwareApplication"}}