{"tool_name":"crosscheck","contents":["bioschemas","biotools"],"page_metadata":{"biotools__id":"crosscheck","biotools__home":"http://proteinguru.com/toolbox/crosscheck/","biotools__summary":"Open-source web tool for high-throughput screen data analysis.","biotools__addition_date":"2018-07-08T12:56:29Z","biotools__last_update_date":"2018-12-10T12:59:00Z","biotools__tool_type":["Web application"],"bioschemas__name":"CrossCheck","bioschemas__home":"https://bio.tools/crosscheck","bioschemas__summary":"Open-source web tool for high-throughput screen data analysis.","bioschemas__tool_type":"sc:SoftwareApplication"}}