{"tool_name":"cstreet","contents":["bioschemas","biotools"],"page_metadata":{"biotools__id":"cstreet","biotools__home":"https://doi.org/10.5281/zenodo.4483205","biotools__license":"MIT","biotools__summary":"A computed Cell State trajectory inference method for time-series single-cell RNA sequencing data.","biotools__addition_date":"2021-11-24T14:55:50.094689Z","biotools__last_update_date":"2021-11-24T14:55:50.097125Z","biotools__tool_type":["Command-line tool","Library"],"bioschemas__name":"CStreet","bioschemas__home":"https://bio.tools/cstreet","bioschemas__license":"MIT","bioschemas__summary":"A computed Cell State trajectory inference method for time-series single-cell RNA sequencing data.","bioschemas__tool_type":"sc:SoftwareApplication"}}