{"tool_name":"deephlapred","contents":["bioschemas","biotools"],"page_metadata":{"biotools__id":"deephlapred","biotools__home":"http://www.biolscience.cn/DeepHLApred/","biotools__summary":"Deep learning-based method for non-classical HLA binder prediction.","biotools__addition_date":"2024-04-19T10:04:52.539998Z","biotools__last_update_date":"2024-11-24T14:03:06.417955Z","biotools__tool_type":["Web application"],"bioschemas__name":"DeepHLAPred","bioschemas__home":"https://bio.tools/deephlapred","bioschemas__summary":"Deep learning-based method for non-classical HLA binder prediction.","bioschemas__tool_type":"sc:SoftwareApplication"}}