{"tool_name":"evihvr","contents":["biotools","bioschemas"],"page_metadata":{"biotools__id":"evihvr","biotools__home":"http://www.computationalbiology.cn/EVIHVR/#/","biotools__summary":"A platform for analysis of expression, variation and identification of human virus receptors.","biotools__addition_date":"2024-04-19T08:28:51.938153Z","biotools__last_update_date":"2024-11-24T14:03:34.593964Z","biotools__tool_type":["Web application"],"bioschemas__name":"EVIHVR","bioschemas__home":"https://bio.tools/evihvr","bioschemas__summary":"A platform for analysis of expression, variation and identification of human virus receptors.","bioschemas__tool_type":"sc:SoftwareApplication"}}