{"tool_name":"fazseg","contents":["bioschemas","biotools"],"page_metadata":{"biotools__id":"fazseg","biotools__home":"https://github.com/VIEKASH2001/FAZSeg","biotools__summary":"A tool to validate newly developed automated segmentation algorithms.","biotools__addition_date":"2022-06-13T10:30:50.804992Z","biotools__last_update_date":"2022-06-13T10:30:50.807593Z","biotools__tool_type":["Desktop application"],"bioschemas__name":"FAZSeg","bioschemas__home":"https://bio.tools/fazseg","bioschemas__summary":"A tool to validate newly developed automated segmentation algorithms.","bioschemas__tool_type":"sc:SoftwareApplication"}}