{"tool_name":"ggd","contents":["bioschemas","biotools","biocontainers"],"page_metadata":{"biocontainers__name":"ggd","biocontainers__license":"MIT","biocontainers__summary":"Gogetdata (ggd) is a genomic data managment system. it provide simple and reproducible access to a repository of genomic data. simply put, it is 'conda' for genomic data","biotools__id":"ggd","biotools__home":"https://github.com/gogetdata/ggd-recipes","biotools__summary":"Go Get Data (GGD) is a framework that facilitates reproducible access to genomic data.","biotools__addition_date":"2021-09-20T09:40:01.970084Z","biotools__last_update_date":"2021-09-20T09:40:01.970486Z","biotools__tool_type":["Workbench"],"bioschemas__name":"GGD","bioschemas__home":"https://bio.tools/ggd","bioschemas__summary":"Go Get Data (GGD) is a framework that facilitates reproducible access to genomic data.","bioschemas__tool_type":"sc:SoftwareApplication"}}