{"tool_name":"grad-seq","contents":["bioschemas","biotools"],"page_metadata":{"biotools__id":"grad-seq","biotools__home":"https://sunshine.biologie.uni-freiburg.de/GradSeqExplorer/","biotools__summary":"Analysis of a photosynthetic cyanobacterium rich in internal membrane systems via gradient profiling by sequencing (Grad-seq).\n\nAnalysis-of-a-photosynthetic-cyanobacterium-rich-in-internal-membrane-systems-via-Grad-seq.","biotools__addition_date":"2021-01-18T10:06:09Z","biotools__last_update_date":"2021-03-18T08:58:42Z","biotools__tool_type":["Web application"],"bioschemas__name":"Grad-seq","bioschemas__home":"https://bio.tools/grad-seq","bioschemas__summary":"Analysis of a photosynthetic cyanobacterium rich in internal membrane systems via gradient profiling by sequencing (Grad-seq).\n\nAnalysis-of-a-photosynthetic-cyanobacterium-rich-in-internal-membrane-systems-via-Grad-seq.","bioschemas__tool_type":"sc:SoftwareApplication"}}