{"tool_name":"gutmicronet","contents":["biotools","bioschemas"],"page_metadata":{"biotools":{"id":"gutmicronet","home":"https://gutmicro.net","license":null,"summary":"An interactive platform for gut microbiome interaction exploration.","addition_date":"2022-05-07T08:54:57.757227Z","last_update_date":"2022-05-07T08:55:29.844633Z","tool_type":["Web application"],"version":null},"bioschemas":{"name":"GutMicroNet","home":"https://bio.tools/gutmicronet","license":null,"version":null,"summary":"An interactive platform for gut microbiome interaction exploration.","tool_type":"sc:SoftwareApplication"}}}