{"tool_name":"identiflow","contents":["biotools","bioschemas"],"page_metadata":{"biotools__id":"identiflow","biotools__home":"http://github.com/GrossTor/IdentiFlow","biotools__license":"MIT","biotools__summary":"Identifiability and experimental design in perturbation studies.\n\nInteraction strengths between nodes in directed networks can be quantified from observations of the network's response to perturbations. This package reveals the identifiability of the inferred network parameters and optimizes experimental design for network perturbation studies. See our publication for details.\n\nYou can install the IdentiFlow package with pip:.","biotools__addition_date":"2021-01-18T10:11:01Z","biotools__last_update_date":"2021-01-30T10:32:09Z","biotools__tool_type":["Library"],"bioschemas__name":"IdentiFlow","bioschemas__home":"https://bio.tools/identiflow","bioschemas__license":"MIT","bioschemas__summary":"Identifiability and experimental design in perturbation studies.\n\nInteraction strengths between nodes in directed networks can be quantified from observations of the network's response to perturbations. This package reveals the identifiability of the inferred network parameters and optimizes experimental design for network perturbation studies. See our publication for details.\n\nYou can install the IdentiFlow package with pip:.","bioschemas__tool_type":"sc:SoftwareApplication"}}