{"tool_name":"imkt","contents":["bioschemas","biotools"],"page_metadata":{"biotools__id":"iMKT","biotools__home":"https://imkt.uab.cat","biotools__license":"GPL-3.0","biotools__summary":"integrative McDonald and Kreitman test.","biotools__addition_date":"2019-08-09T13:05:42Z","biotools__last_update_date":"2020-06-16T10:55:25Z","biotools__tool_type":["Library","Web application"],"bioschemas__name":"iMKT","bioschemas__home":"https://bio.tools/iMKT","bioschemas__license":"GPL-3.0","bioschemas__summary":"integrative McDonald and Kreitman test.","bioschemas__tool_type":"sc:SoftwareApplication"}}