{"tool_name":"mapsembler","contents":["bioschemas","biotools"],"page_metadata":{"biotools__id":"mapsembler","biotools__home":"https://colibread.inria.fr/mapsembler2/","biotools__license":"AGPL-3.0","biotools__summary":"A targeted assembly software.","biotools__addition_date":"2015-01-21T15:12:22Z","biotools__last_update_date":"2024-11-25T16:06:22.558427Z","biotools__tool_type":["Command-line tool"],"biotools__version":["2.2.4"],"bioschemas__name":"Mapsembler","bioschemas__home":"https://bio.tools/mapsembler","bioschemas__license":"AGPL-3.0","bioschemas__version":"2.2.4","bioschemas__summary":"A targeted assembly software.","bioschemas__tool_type":"sc:SoftwareApplication"}}