{"tool_name":"medna-metadata","contents":["bioschemas","biotools"],"page_metadata":{"biotools__id":"medna-metadata","biotools__home":"https://demo.metadata.maine-edna.org/","biotools__license":"GPL-3.0","biotools__summary":"An open-source data management system for tracking environmental DNA samples and metadata.","biotools__addition_date":"2022-10-19T19:48:31.210660Z","biotools__last_update_date":"2022-10-19T19:48:54.478206Z","biotools__tool_type":["Web application"],"bioschemas__name":"medna-metadata","bioschemas__home":"https://bio.tools/medna-metadata","bioschemas__license":"GPL-3.0","bioschemas__summary":"An open-source data management system for tracking environmental DNA samples and metadata.","bioschemas__tool_type":"sc:SoftwareApplication"}}