{"tool_name":"mendelianrandomization","contents":["bioschemas","biotools"],"page_metadata":{"biotools__id":"mendelianrandomization","biotools__home":"https://cran.r-project.org/web/packages/MendelianRandomization/","biotools__summary":"Encodes several methods for performing Mendelian randomization analyses with summarized data. Summarized data on genetic associations with the exposure and with the outcome can be obtained from large consortia. These data can be used for obtaining causal estimates using instrumental variable methods.","biotools__addition_date":"2018-07-28T09:34:01Z","biotools__last_update_date":"2018-12-10T12:59:00Z","biotools__tool_type":["Library"],"bioschemas__name":"MendelianRandomization","bioschemas__home":"https://bio.tools/mendelianrandomization","bioschemas__summary":"Encodes several methods for performing Mendelian randomization analyses with summarized data. Summarized data on genetic associations with the exposure and with the outcome can be obtained from large consortia. These data can be used for obtaining causal estimates using instrumental variable methods.","bioschemas__tool_type":"sc:SoftwareApplication"}}