{"tool_name":"mzxmlplot","contents":["biotools","bioschemas"],"page_metadata":{"biotools__id":"mzxmlplot","biotools__home":"http://www.ms-utils.org/mzXMLplot/index.html","biotools__summary":"Plots mzXML LC-MS data as virtual gels or heat maps.","biotools__addition_date":"2017-01-17T14:50:38Z","biotools__last_update_date":"2019-03-26T08:28:02Z","biotools__tool_type":["Command-line tool"],"bioschemas__name":"mzXMLplot","bioschemas__home":"https://bio.tools/mzxmlplot","bioschemas__summary":"Plots mzXML LC-MS data as virtual gels or heat maps.","bioschemas__tool_type":"sc:SoftwareApplication"}}