{"tool_name":"nicebot","contents":["bioschemas","biotools"],"page_metadata":{"biotools__id":"NiceBot","biotools__home":"https://github.com/TNTLFreiburg/NiceBot","biotools__summary":"Inferring Continuous Subjective Ratings With Deep Regression.\n\nData and code of the BrainLinks-BrainTools NiceBot project, manuscript \"Human-Compliant Robot Behavior: Combining Continuous Subjective Evaluation with Multimodal Deep Regression Analysis\".","biotools__addition_date":"2020-01-09T18:22:52Z","biotools__last_update_date":"2021-01-04T08:22:44Z","biotools__tool_type":["Library"],"bioschemas__name":"NiceBot","bioschemas__home":"https://bio.tools/NiceBot","bioschemas__summary":"Inferring Continuous Subjective Ratings With Deep Regression.\n\nData and code of the BrainLinks-BrainTools NiceBot project, manuscript \"Human-Compliant Robot Behavior: Combining Continuous Subjective Evaluation with Multimodal Deep Regression Analysis\".","bioschemas__tool_type":"sc:SoftwareApplication"}}