{"tool_name":"pave","contents":["biotools","bioschemas"],"page_metadata":{"biotools":{"id":"pave","home":"https://github.com/yinchangchang/PAVE","license":null,"summary":"An Interpretable Risk Prediction Model for Healthcare with Pattern Attention.\n\nPattern Attention Model with Value Embedding (PAVE).","addition_date":"2021-01-18T09:59:07Z","last_update_date":"2021-01-23T06:33:06Z","tool_type":null,"version":null},"bioschemas":{"name":"PAVE","home":"https://bio.tools/pave","license":null,"version":null,"summary":"An Interpretable Risk Prediction Model for Healthcare with Pattern Attention.\n\nPattern Attention Model with Value Embedding (PAVE).","tool_type":"sc:SoftwareApplication"}}}