{"tool_name":"phewas_clinical","contents":["biotools","bioschemas"],"page_metadata":{"biotools__id":"phewas_clinical","biotools__home":"https://github.com/PheWAS/PheWAS","biotools__summary":"Evaluating statistical approaches to leverage large clinical datasets for uncovering therapeutic and adverse medication effects.","biotools__addition_date":"2018-06-01T16:27:45Z","biotools__last_update_date":"2024-11-25T14:36:39.789094Z","biotools__tool_type":["Library"],"bioschemas__name":"PheWAS","bioschemas__home":"https://bio.tools/phewas_clinical","bioschemas__summary":"Evaluating statistical approaches to leverage large clinical datasets for uncovering therapeutic and adverse medication effects.","bioschemas__tool_type":"sc:SoftwareApplication"}}