{"tool_name":"piphillin","contents":["bioschemas","biotools"],"page_metadata":{"biotools__id":"piphillin","biotools__home":"http://secondgenome.com/solutions/resources/data-analysis-tools/piphillin/","biotools__summary":"Improved Prediction of Metagenomic Content by Direct Inference from Human Microbiomes.","biotools__addition_date":"2018-05-29T10:31:19Z","biotools__last_update_date":"2018-12-10T12:58:58Z","biotools__tool_type":["Web application"],"bioschemas__name":"Piphillin","bioschemas__home":"https://bio.tools/piphillin","bioschemas__summary":"Improved Prediction of Metagenomic Content by Direct Inference from Human Microbiomes.","bioschemas__tool_type":"sc:SoftwareApplication"}}