{"tool_name":"psrnatarget","contents":["bioschemas","biotools"],"page_metadata":{"biotools__id":"psrnatarget","biotools__home":"http://plantgrn.noble.org/psRNATarget/.","biotools__summary":"psRNATarget is a plant small RNA target analysis server which features reverse complementary matching between small RNA and target transcript, and target site accessibility evaluation. It is designed for high-throughput analysis of next generation data, and outputs a comprehensive list of small RNA-target pairs.","biotools__addition_date":"2017-02-14T09:35:34Z","biotools__last_update_date":"2018-12-10T12:58:56Z","biotools__tool_type":["Web application"]}}