{"tool_name":"py-em","contents":["biotools","bioschemas"],"page_metadata":{"biotools__id":"Py-EM","biotools__home":"https://git.embl.de/schorb/pyem","biotools__license":"GPL-3.0","biotools__summary":"Software tools for automated transmission electron microscopy.","biotools__addition_date":"2019-08-09T13:20:47Z","biotools__last_update_date":"2020-06-16T10:55:26Z","biotools__tool_type":["Library"],"bioschemas__name":"Py-EM","bioschemas__home":"https://bio.tools/Py-EM","bioschemas__license":"GPL-3.0","bioschemas__summary":"Software tools for automated transmission electron microscopy.","bioschemas__tool_type":"sc:SoftwareApplication"}}