{"tool_name":"py2dic","contents":["bioschemas","biotools"],"page_metadata":{"biotools__id":"py2DIC","biotools__home":"http://github.com/Geod-Geom/py2DIC/","biotools__license":"GPL-3.0","biotools__summary":"A New Free and Open Source Software for Displacement and Strain Measurements in the Field of Experimental Mechanics | py2DIC is a free and open source software for 2D DIC developed at the Geodesy and Geomatics Division, University of Rome \"La Sapienza\" | pydic is a free suite of python tools for local digital image correlation analysis","biotools__addition_date":"2019-11-14T19:40:41Z","biotools__last_update_date":"2020-12-10T12:53:20Z","bioschemas__name":"py2DIC","bioschemas__home":"https://bio.tools/py2DIC","bioschemas__license":"GPL-3.0","bioschemas__summary":"A New Free and Open Source Software for Displacement and Strain Measurements in the Field of Experimental Mechanics | py2DIC is a free and open source software for 2D DIC developed at the Geodesy and Geomatics Division, University of Rome \"La Sapienza\" | pydic is a free suite of python tools for local digital image correlation analysis","bioschemas__tool_type":"sc:SoftwareApplication"}}