{"tool_name":"q-omics","contents":["biotools","bioschemas"],"page_metadata":{"biotools__id":"q-omics","biotools__home":"http://qomics.sookmyung.ac.kr","biotools__summary":"Smart Software for Assisting Oncology and Cancer Research.","biotools__addition_date":"2022-05-17T18:18:13.434690Z","biotools__last_update_date":"2022-05-17T18:18:13.437194Z","biotools__tool_type":["Desktop application"],"bioschemas__name":"Q-omics","bioschemas__home":"https://bio.tools/q-omics","bioschemas__summary":"Smart Software for Assisting Oncology and Cancer Research.","bioschemas__tool_type":"sc:SoftwareApplication"}}