{"tool_name":"reactioncode","contents":["biotools","bioschemas"],"page_metadata":{"biotools":{"id":"reactioncode","home":"https://cactus.nci.nih.gov/reactioncode","license":null,"summary":"Format for Reaction Searching, Analysis, Classification, Transform, and Encoding/Decoding.\n\nReactionCode is a new versatile format for searching, analysis, classification, transform, and encoding decoding of reactions.","addition_date":"2021-01-18T10:12:05Z","last_update_date":"2021-02-04T15:13:55Z","tool_type":null,"version":null},"bioschemas":{"name":"ReactionCode","home":"https://bio.tools/reactioncode","license":null,"version":null,"summary":"Format for Reaction Searching, Analysis, Classification, Transform, and Encoding/Decoding.\n\nReactionCode is a new versatile format for searching, analysis, classification, transform, and encoding decoding of reactions.","tool_type":"sc:SoftwareApplication"}}}