{"tool_name":"riboswitch_scanner","contents":["bioschemas","biotools"],"page_metadata":{"biotools__id":"riboswitch_scanner","biotools__home":"http://service.iiserkol.ac.in/~riboscan/","biotools__summary":"A new web application which provides an automated pipeline for pHMM-based detection of riboswitches in partial as well as complete genomic sequences rapidly, with high sensitivity and specificity.","biotools__addition_date":"2017-08-03T18:58:45Z","biotools__last_update_date":"2024-11-25T16:08:59.637304Z","biotools__tool_type":["Web application"],"bioschemas__name":"Riboswitch Scanner","bioschemas__home":"https://bio.tools/riboswitch_scanner","bioschemas__summary":"A new web application which provides an automated pipeline for pHMM-based detection of riboswitches in partial as well as complete genomic sequences rapidly, with high sensitivity and specificity.","bioschemas__tool_type":"sc:SoftwareApplication"}}