{"tool_name":"scdreamer","contents":["biotools","bioschemas"],"page_metadata":{"biotools__id":"scdreamer","biotools__home":"https://github.com/Zafar-Lab/scDREAMER","biotools__license":"MIT","biotools__summary":"Atlas-level integration of single-cell datasets using deep generative model paired with adversarial classifier.","biotools__addition_date":"2024-06-18T13:37:45.175760Z","biotools__last_update_date":"2024-11-24T13:54:19.018748Z","biotools__tool_type":["Library"],"bioschemas__name":"scDREAMER","bioschemas__home":"https://bio.tools/scdreamer","bioschemas__license":"MIT","bioschemas__summary":"Atlas-level integration of single-cell datasets using deep generative model paired with adversarial classifier.","bioschemas__tool_type":"sc:SoftwareApplication"}}