{"tool_name":"survbin","contents":["biotools","bioschemas"],"page_metadata":{"biotools__id":"survbin","biotools__home":"https://github.com/MartaBofillRoig/SurvBin","biotools__license":"Not licensed","biotools__summary":"A class of two-sample nonparametric statistics for binary and time-to-event outcomes.","biotools__addition_date":"2022-05-16T20:38:40.155661Z","biotools__last_update_date":"2022-05-16T20:38:40.158252Z","biotools__tool_type":["Library"],"bioschemas__name":"SurvBin","bioschemas__home":"https://bio.tools/survbin","bioschemas__license":"Not licensed","bioschemas__summary":"A class of two-sample nonparametric statistics for binary and time-to-event outcomes.","bioschemas__tool_type":"sc:SoftwareApplication"}}