{"tool_name":"vessap","contents":["bioschemas","biotools"],"page_metadata":{"biotools__id":"vessap","biotools__home":"http://DISCOtechnologies.org/VesSAP","biotools__summary":"VesSAP: Vessel Segmentation & Analysis Pipeline. Machine learning analysis of whole mouse brain vasculature.","biotools__addition_date":"2021-01-18T08:13:33Z","biotools__last_update_date":"2021-03-12T16:16:41Z","bioschemas__name":"VesSAP","bioschemas__home":"https://bio.tools/vessap","bioschemas__summary":"VesSAP: Vessel Segmentation & Analysis Pipeline. Machine learning analysis of whole mouse brain vasculature.","bioschemas__tool_type":"sc:SoftwareApplication"}}