{"tool_name":"vg","contents":["bioschemas","biotools","biocontainers"],"page_metadata":{"biocontainers__name":"vg","biocontainers__license":"MIT","biocontainers__summary":"Variation graph data structures, interchange formats, alignment, genotyping, and variant calling methods","biotools__id":"vg","biotools__home":"https://github.com/vgteam/vg","biotools__summary":"variation graph data structures, interchange formats, alignment, genotyping, and variant calling methods","biotools__addition_date":"2021-04-22T20:01:51Z","biotools__last_update_date":"2021-04-22T20:03:19Z","biotools__version":["1.32.0"]}}