{"tool_name":"vitviz","contents":["bioschemas","biotools"],"page_metadata":{"biotools__id":"vitviz","biotools__home":"https://tomsbiolab.com/vitviz","biotools__summary":"Transcriptomic and metabolomic integration as a resource in grapevine to study fruit metabolite quality traits.","biotools__addition_date":"2023-01-24T15:35:14.493636Z","biotools__last_update_date":"2023-01-24T15:35:14.496536Z","biotools__tool_type":["Web application"],"bioschemas__name":"VitViz","bioschemas__home":"https://bio.tools/vitviz","bioschemas__summary":"Transcriptomic and metabolomic integration as a resource in grapevine to study fruit metabolite quality traits.","bioschemas__tool_type":"sc:SoftwareApplication"}}