{"tool_name":"wormnet_v3","contents":["biotools","bioschemas"],"page_metadata":{"biotools__id":"wormnet_v3","biotools__home":"http://www.inetbio.org/wormnet","biotools__summary":"Network-assisted hypothesis-generating web server for Caenorhabditis elegans.","biotools__addition_date":"2017-05-16T13:58:51Z","biotools__last_update_date":"2018-12-10T12:58:52Z","biotools__tool_type":["Web application"],"bioschemas__name":"WormNet v3","bioschemas__home":"https://bio.tools/wormnet_v3","bioschemas__summary":"Network-assisted hypothesis-generating web server for Caenorhabditis elegans.","bioschemas__tool_type":"sc:SoftwareApplication"}}